scsit/__init__.py
scsit/cfunction.so
scsit_tools-1.0.1.data/scripts/scsit
scsit_tools-1.0.1.dist-info/LICENSE
scsit_tools-1.0.1.dist-info/METADATA
scsit_tools-1.0.1.dist-info/WHEEL
scsit_tools-1.0.1.dist-info/top_level.txt
scsit_tools-1.0.1.dist-info/RECORD
